cmake_file_api/__init__.py
cmake_file_api/cmake.py
cmake_file_api/errors.py
cmake_file_api/py.typed
cmake_file_api/kinds/__init__.py
cmake_file_api/kinds/api.py
cmake_file_api/kinds/common.py
cmake_file_api/kinds/kind.py
cmake_file_api/kinds/cache/__init__.py
cmake_file_api/kinds/cache/api.py
cmake_file_api/kinds/cache/v2.py
cmake_file_api/kinds/cmakeFiles/__init__.py
cmake_file_api/kinds/cmakeFiles/api.py
cmake_file_api/kinds/cmakeFiles/v1.py
cmake_file_api/kinds/codemodel/__init__.py
cmake_file_api/kinds/codemodel/api.py
cmake_file_api/kinds/codemodel/v2.py
cmake_file_api/kinds/codemodel/target/__init__.py
cmake_file_api/kinds/codemodel/target/api.py
cmake_file_api/kinds/codemodel/target/v2.py
cmake_file_api/kinds/configureLog/__init__.py
cmake_file_api/kinds/configureLog/api.py
cmake_file_api/kinds/configureLog/v1.py
cmake_file_api/kinds/configureLog/target/__init__.py
cmake_file_api/kinds/configureLog/target/api.py
cmake_file_api/kinds/configureLog/target/v2.py
cmake_file_api/kinds/toolchains/__init__.py
cmake_file_api/kinds/toolchains/api.py
cmake_file_api/kinds/toolchains/v1.py
cmake_file_api/reply/__init__.py
cmake_file_api/reply/api.py
cmake_file_api/reply/index/__init__.py
cmake_file_api/reply/index/api.py
cmake_file_api/reply/index/v1.py
cmake_file_api/reply/index/file/__init__.py
cmake_file_api/reply/index/file/api.py
cmake_file_api/reply/index/file/v1.py
cmake_file_api/reply/v1/__init__.py
cmake_file_api/reply/v1/api.py
cmake_file_api-0.0.8.6.dist-info/licenses/COPYING
cmake_file_api-0.0.8.6.dist-info/METADATA
cmake_file_api-0.0.8.6.dist-info/WHEEL
cmake_file_api-0.0.8.6.dist-info/top_level.txt
cmake_file_api-0.0.8.6.dist-info/RECORD
