Metadata-Version: 2.4
Name: cmake-file-api
Version: 0.0.8.6
Summary: Read and interpret CMake's file-based API
Home-page: http://github.com/madebr/python-cmake-file-api
Author: Anonymous Maarten
Author-email: anonymous.maarten@gmail.com
License: MIT
Classifier: Development Status :: 1 - Planning
Classifier: Programming Language :: Python :: 3
Classifier: Programming Language :: C
Classifier: Programming Language :: C++
Classifier: License :: OSI Approved :: MIT License
Classifier: Operating System :: OS Independent
Requires-Python: >=3.10
License-File: COPYING
Dynamic: license-file
